plex_default_settings/__init__.py
plex_default_settings/main.py
plex_default_settings-0.1.4.dist-info/LICENSE
plex_default_settings-0.1.4.dist-info/METADATA
plex_default_settings-0.1.4.dist-info/WHEEL
plex_default_settings-0.1.4.dist-info/entry_points.txt
plex_default_settings-0.1.4.dist-info/top_level.txt
plex_default_settings-0.1.4.dist-info/RECORD
