Metadata-Version: 2.1
Name: plex-default-settings
Version: 0.1.4
Summary: Plex default settings
Home-page: https://github.com/antonlabs/plex_default_settings
Author: Anton Kuzmenko
Author-email: hotk@hey.com
License: UNKNOWN
Project-URL: Bug Reports, https://github.com/antonlabs/plex_default_settings/issues
Project-URL: Source, https://github.com/antonlabs/plex_default_settings
Keywords: plex,subtitles,dubbing,subs,dubs
Platform: UNKNOWN
Classifier: Development Status :: 3 - Alpha
Classifier: Intended Audience :: End Users/Desktop
Classifier: Topic :: Multimedia
Classifier: Topic :: Multimedia :: Video
Classifier: Topic :: Multimedia :: Video :: Display
Classifier: Topic :: Utilities
Classifier: License :: OSI Approved :: MIT License
Classifier: Programming Language :: Python :: 3.8
Classifier: Programming Language :: Python :: 3.9
Requires-Python: >=3.8, <4
Requires-Dist: plexapi (==4.2.0)
Requires-Dist: typer (==0.3.2)
